pygame_timer/__init__.py
pygame_timer/activation_timer.py
pygame_timer/cooldown_timer.py
pygame_timer/interval_timer.py
pygame_timer/stopwatch_timer.py
pygame_timer/target_timer.py
pygame_timer/timer.py
pygame_timer-1.0.0.dist-info/METADATA
pygame_timer-1.0.0.dist-info/WHEEL
pygame_timer-1.0.0.dist-info/top_level.txt
pygame_timer-1.0.0.dist-info/RECORD
