Metadata-Version: 2.1
Name: pygame-timer
Version: 1.0.0
Summary: A package for various types of timers
Home-page: https://github.com/FrickTzy/Pygame-Timer
Author: FrickTzy (Kurt Arnoco)
License: UNKNOWN
Keywords: python,pygame,python game,python game development,pygame timer
Platform: UNKNOWN
Requires-Dist: pygame
